jockey/__init__.py
jockey/_actor.py
jockey/_adapter.py
jockey/_execute_in.py
jockey/_executor.py
jockey/_priority.py
jockey/_registry.py
jockey/_tasks.py
jockey/_wait_for.py
jockey/py.typed
jockey-1.0.0.dist-info/LICENSE
jockey-1.0.0.dist-info/WHEEL
jockey-1.0.0.dist-info/METADATA
jockey-1.0.0.dist-info/RECORD
