Metadata-Version: 2.1
Name: jockey
Version: 1.0.0
Summary: Generic and type safe runner for asynchronous workers.
Keywords: microservices,event-driven,distributed,web,framewrok,web framework,asyncio,kafka,nats,rabbitmq,arq,celery,dramatiq,huey,rq,walnats
Author-email: Gram <git@orsinium.dev>
Requires-Python: >=3.8
Classifier: Development Status :: 5 - Production/Stable
Classifier: Intended Audience :: Developers
Classifier: License :: OSI Approved :: MIT License
Classifier: Programming Language :: Python
Classifier: Typing :: Typed
Requires-Dist: ruff ; extra == "lint"
Requires-Dist: mypy ; extra == "lint"
Requires-Dist: hypothesis ; extra == "test"
Requires-Dist: pytest ; extra == "test"
Requires-Dist: pytest-cov ; extra == "test"
Requires-Dist: pytest-asyncio ; extra == "test"
Project-URL: Source, https://github.com/orsinium-labs/jockey
Provides-Extra: lint
Provides-Extra: test
